{
    "data": {
        "asg_parameter": {
            "grouppertargetnumlimit": "3",
            "grouproundnumlimit": "1",
            "maxthreadnumlimit": "0",
            "targetpergroupnumlimit": "5"
        },
        "base_data": {
            "base_deptimeinterval": "0.148773",
            "base_name": "base1",
            "base_position": "116.325925,39.908484"
        },
        "forces_list": [
            {
                "force_id": "force_0",
                "force_position": "116.462045,39.864356",
                "force_type": "plane1",
                "fuel_cost": "0.594829",
                "max_distance": "10",
                "max_speed": "58",
                "min_speed": "22",
                "preparation_time": "17",
                "setup_cost": "0.612132",
                "weapon_num": "30",
                "weapon_type": "mount1"
            },
            {
                "force_id": "force_1",
                "force_position": "116.309431,39.817616",
                "force_type": "vehical2",
                "fuel_cost": "0.221029",
                "max_distance": "19",
                "max_speed": "41",
                "min_speed": "16",
                "preparation_time": "15",
                "setup_cost": "0.866649",
                "weapon_num": "30",
                "weapon_type": "mount5"
            },
            {
                "force_id": "force_2",
                "force_position": "116.321199,39.861485",
                "force_type": "plane2",
                "fuel_cost": "0.403770",
                "max_distance": "39",
                "max_speed": "55",
                "min_speed": "23",
                "preparation_time": "13",
                "setup_cost": "0.620572",
                "weapon_num": "50,50",
                "weapon_type": "mount2,mount3"
            },
            {
                "force_id": "force_3",
                "force_position": "116.384604,39.923617",
                "force_type": "plane1",
                "fuel_cost": "0.298003",
                "max_distance": "11",
                "max_speed": "54",
                "min_speed": "13",
                "preparation_time": "12",
                "setup_cost": "0.897099",
                "weapon_num": "30",
                "weapon_type": "mount1"
            },
            {
                "force_id": "force_4",
                "force_position": "116.405176,39.780634",
                "force_type": "plane2",
                "fuel_cost": "0.396694",
                "max_distance": "22",
                "max_speed": "65",
                "min_speed": "35",
                "preparation_time": "20",
                "setup_cost": "0.162654",
                "weapon_num": "50,50",
                "weapon_type": "mount2,mount3"
            },
            {
                "force_id": "force_5",
                "force_position": "116.450521,40.029790",
                "force_type": "vehical2",
                "fuel_cost": "0.411953",
                "max_distance": "15",
                "max_speed": "51",
                "min_speed": "38",
                "preparation_time": "22",
                "setup_cost": "0.953040",
                "weapon_num": "30",
                "weapon_type": "mount5"
            },
            {
                "force_id": "force_6",
                "force_position": "116.420581,39.954066",
                "force_type": "vehical2",
                "fuel_cost": "0.804511",
                "max_distance": "14",
                "max_speed": "53",
                "min_speed": "28",
                "preparation_time": "11",
                "setup_cost": "0.134822",
                "weapon_num": "30",
                "weapon_type": "mount5"
            },
            {
                "force_id": "force_7",
                "force_position": "116.362832,39.917733",
                "force_type": "vehical2",
                "fuel_cost": "0.726988",
                "max_distance": "23",
                "max_speed": "40",
                "min_speed": "18",
                "preparation_time": "37",
                "setup_cost": "0.411255",
                "weapon_num": "30",
                "weapon_type": "mount5"
            },
            {
                "force_id": "force_8",
                "force_position": "116.434249,39.953538",
                "force_type": "plane1",
                "fuel_cost": "0.811618",
                "max_distance": "31",
                "max_speed": "80",
                "min_speed": "35",
                "preparation_time": "33",
                "setup_cost": "0.824159",
                "weapon_num": "30",
                "weapon_type": "mount1"
            },
            {
                "force_id": "force_9",
                "force_position": "116.450738,39.913696",
                "force_type": "plane1",
                "fuel_cost": "0.403957",
                "max_distance": "16",
                "max_speed": "62",
                "min_speed": "22",
                "preparation_time": "24",
                "setup_cost": "0.144478",
                "weapon_num": "30",
                "weapon_type": "mount1"
            },
            {
                "force_id": "force_10",
                "force_position": "116.413259,39.842583",
                "force_type": "plane1",
                "fuel_cost": "0.901810",
                "max_distance": "12",
                "max_speed": "40",
                "min_speed": "18",
                "preparation_time": "27",
                "setup_cost": "0.580008",
                "weapon_num": "30",
                "weapon_type": "mount1"
            },
            {
                "force_id": "force_11",
                "force_position": "116.443354,39.859511",
                "force_type": "vehical2",
                "fuel_cost": "0.594449",
                "max_distance": "13",
                "max_speed": "45",
                "min_speed": "18",
                "preparation_time": "22",
                "setup_cost": "0.198580",
                "weapon_num": "30",
                "weapon_type": "mount5"
            },
            {
                "force_id": "force_12",
                "force_position": "116.311750,40.038962",
                "force_type": "vehical1",
                "fuel_cost": "0.906419",
                "max_distance": "14",
                "max_speed": "62",
                "min_speed": "34",
                "preparation_time": "40",
                "setup_cost": "0.295641",
                "weapon_num": "40",
                "weapon_type": "mount4"
            },
            {
                "force_id": "force_13",
                "force_position": "116.354709,40.019307",
                "force_type": "plane1",
                "fuel_cost": "0.739864",
                "max_distance": "17",
                "max_speed": "69",
                "min_speed": "40",
                "preparation_time": "39",
                "setup_cost": "0.954319",
                "weapon_num": "30",
                "weapon_type": "mount1"
            },
            {
                "force_id": "force_14",
                "force_position": "116.466862,39.892316",
                "force_type": "plane1",
                "fuel_cost": "0.213871",
                "max_distance": "35",
                "max_speed": "62",
                "min_speed": "15",
                "preparation_time": "19",
                "setup_cost": "0.680082",
                "weapon_num": "30",
                "weapon_type": "mount1"
            },
            {
                "force_id": "force_15",
                "force_position": "116.366174,39.825980",
                "force_type": "plane2",
                "fuel_cost": "0.941554",
                "max_distance": "27",
                "max_speed": "61",
                "min_speed": "35",
                "preparation_time": "39",
                "setup_cost": "0.715499",
                "weapon_num": "50,50",
                "weapon_type": "mount2,mount3"
            },
            {
                "force_id": "force_16",
                "force_position": "116.470295,39.835259",
                "force_type": "plane1",
                "fuel_cost": "0.615910",
                "max_distance": "14",
                "max_speed": "40",
                "min_speed": "11",
                "preparation_time": "28",
                "setup_cost": "0.862565",
                "weapon_num": "30",
                "weapon_type": "mount1"
            },
            {
                "force_id": "force_17",
                "force_position": "116.416949,39.953059",
                "force_type": "vehical1",
                "fuel_cost": "0.128260",
                "max_distance": "39",
                "max_speed": "50",
                "min_speed": "10",
                "preparation_time": "14",
                "setup_cost": "0.484686",
                "weapon_num": "40",
                "weapon_type": "mount4"
            },
            {
                "force_id": "force_18",
                "force_position": "116.441492,39.832524",
                "force_type": "vehical2",
                "fuel_cost": "0.487246",
                "max_distance": "29",
                "max_speed": "54",
                "min_speed": "39",
                "preparation_time": "29",
                "setup_cost": "0.640455",
                "weapon_num": "30",
                "weapon_type": "mount5"
            },
            {
                "force_id": "force_19",
                "force_position": "116.411507,39.888233",
                "force_type": "vehical2",
                "fuel_cost": "0.905451",
                "max_distance": "24",
                "max_speed": "61",
                "min_speed": "31",
                "preparation_time": "19",
                "setup_cost": "0.726212",
                "weapon_num": "30",
                "weapon_type": "mount5"
            },
            {
                "force_id": "force_20",
                "force_position": "116.438549,39.931177",
                "force_type": "plane1",
                "fuel_cost": "0.829072",
                "max_distance": "16",
                "max_speed": "50",
                "min_speed": "20",
                "preparation_time": "39",
                "setup_cost": "0.267258",
                "weapon_num": "30",
                "weapon_type": "mount1"
            },
            {
                "force_id": "force_21",
                "force_position": "116.386996,39.930999",
                "force_type": "vehical2",
                "fuel_cost": "0.070136",
                "max_distance": "18",
                "max_speed": "43",
                "min_speed": "20",
                "preparation_time": "33",
                "setup_cost": "0.181535",
                "weapon_num": "30",
                "weapon_type": "mount5"
            },
            {
                "force_id": "force_22",
                "force_position": "116.346010,39.865581",
                "force_type": "vehical1",
                "fuel_cost": "0.961658",
                "max_distance": "23",
                "max_speed": "61",
                "min_speed": "32",
                "preparation_time": "36",
                "setup_cost": "0.779888",
                "weapon_num": "40",
                "weapon_type": "mount4"
            },
            {
                "force_id": "force_23",
                "force_position": "116.479697,39.984709",
                "force_type": "plane1",
                "fuel_cost": "0.479505",
                "max_distance": "32",
                "max_speed": "79",
                "min_speed": "25",
                "preparation_time": "20",
                "setup_cost": "0.994815",
                "weapon_num": "30",
                "weapon_type": "mount1"
            },
            {
                "force_id": "force_24",
                "force_position": "116.337293,40.026894",
                "force_type": "plane2",
                "fuel_cost": "0.815478",
                "max_distance": "15",
                "max_speed": "64",
                "min_speed": "28",
                "preparation_time": "36",
                "setup_cost": "0.714785",
                "weapon_num": "50,50",
                "weapon_type": "mount2,mount3"
            },
            {
                "force_id": "force_25",
                "force_position": "116.397983,39.854297",
                "force_type": "vehical1",
                "fuel_cost": "0.321292",
                "max_distance": "26",
                "max_speed": "77",
                "min_speed": "16",
                "preparation_time": "34",
                "setup_cost": "0.486016",
                "weapon_num": "40",
                "weapon_type": "mount4"
            },
            {
                "force_id": "force_26",
                "force_position": "116.387538,40.038967",
                "force_type": "vehical2",
                "fuel_cost": "0.111616",
                "max_distance": "23",
                "max_speed": "75",
                "min_speed": "25",
                "preparation_time": "40",
                "setup_cost": "0.272950",
                "weapon_num": "30",
                "weapon_type": "mount5"
            },
            {
                "force_id": "force_27",
                "force_position": "116.337815,39.894084",
                "force_type": "plane2",
                "fuel_cost": "0.211581",
                "max_distance": "32",
                "max_speed": "62",
                "min_speed": "30",
                "preparation_time": "19",
                "setup_cost": "0.589731",
                "weapon_num": "50,50",
                "weapon_type": "mount2,mount3"
            },
            {
                "force_id": "force_28",
                "force_position": "116.397839,39.870380",
                "force_type": "plane1",
                "fuel_cost": "0.581712",
                "max_distance": "30",
                "max_speed": "51",
                "min_speed": "33",
                "preparation_time": "35",
                "setup_cost": "0.723626",
                "weapon_num": "30",
                "weapon_type": "mount1"
            },
            {
                "force_id": "force_29",
                "force_position": "116.429470,39.790344",
                "force_type": "vehical1",
                "fuel_cost": "0.327535",
                "max_distance": "27",
                "max_speed": "47",
                "min_speed": "17",
                "preparation_time": "20",
                "setup_cost": "0.969067",
                "weapon_num": "40",
                "weapon_type": "mount4"
            },
            {
                "force_id": "force_30",
                "force_position": "116.485475,40.029807",
                "force_type": "vehical2",
                "fuel_cost": "0.232250",
                "max_distance": "36",
                "max_speed": "41",
                "min_speed": "16",
                "preparation_time": "23",
                "setup_cost": "0.015470",
                "weapon_num": "30",
                "weapon_type": "mount5"
            },
            {
                "force_id": "force_31",
                "force_position": "116.317704,39.959752",
                "force_type": "plane1",
                "fuel_cost": "0.692576",
                "max_distance": "24",
                "max_speed": "76",
                "min_speed": "24",
                "preparation_time": "31",
                "setup_cost": "0.992046",
                "weapon_num": "30",
                "weapon_type": "mount1"
            },
            {
                "force_id": "force_32",
                "force_position": "116.315710,39.824400",
                "force_type": "plane1",
                "fuel_cost": "0.170779",
                "max_distance": "10",
                "max_speed": "63",
                "min_speed": "34",
                "preparation_time": "28",
                "setup_cost": "0.534726",
                "weapon_num": "30",
                "weapon_type": "mount1"
            },
            {
                "force_id": "force_33",
                "force_position": "116.397092,39.883401",
                "force_type": "plane2",
                "fuel_cost": "0.681802",
                "max_distance": "26",
                "max_speed": "73",
                "min_speed": "37",
                "preparation_time": "38",
                "setup_cost": "0.577156",
                "weapon_num": "50,50",
                "weapon_type": "mount2,mount3"
            },
            {
                "force_id": "force_34",
                "force_position": "116.314415,39.785090",
                "force_type": "plane1",
                "fuel_cost": "0.524158",
                "max_distance": "28",
                "max_speed": "47",
                "min_speed": "37",
                "preparation_time": "37",
                "setup_cost": "0.364468",
                "weapon_num": "30",
                "weapon_type": "mount1"
            },
            {
                "force_id": "force_35",
                "force_position": "116.468254,39.842623",
                "force_type": "plane2",
                "fuel_cost": "0.832217",
                "max_distance": "20",
                "max_speed": "49",
                "min_speed": "26",
                "preparation_time": "27",
                "setup_cost": "0.819522",
                "weapon_num": "50,50",
                "weapon_type": "mount2,mount3"
            },
            {
                "force_id": "force_36",
                "force_position": "116.446955,39.830888",
                "force_type": "vehical1",
                "fuel_cost": "0.652097",
                "max_distance": "10",
                "max_speed": "72",
                "min_speed": "40",
                "preparation_time": "16",
                "setup_cost": "0.389363",
                "weapon_num": "40",
                "weapon_type": "mount4"
            },
            {
                "force_id": "force_37",
                "force_position": "116.318076,39.840933",
                "force_type": "plane2",
                "fuel_cost": "0.572654",
                "max_distance": "25",
                "max_speed": "54",
                "min_speed": "12",
                "preparation_time": "31",
                "setup_cost": "0.023602",
                "weapon_num": "50,50",
                "weapon_type": "mount2,mount3"
            },
            {
                "force_id": "force_38",
                "force_position": "116.387686,39.965136",
                "force_type": "plane1",
                "fuel_cost": "0.264869",
                "max_distance": "16",
                "max_speed": "59",
                "min_speed": "37",
                "preparation_time": "15",
                "setup_cost": "0.120193",
                "weapon_num": "30",
                "weapon_type": "mount1"
            },
            {
                "force_id": "force_39",
                "force_position": "116.424024,39.823958",
                "force_type": "vehical1",
                "fuel_cost": "0.324288",
                "max_distance": "16",
                "max_speed": "49",
                "min_speed": "23",
                "preparation_time": "24",
                "setup_cost": "0.623565",
                "weapon_num": "40",
                "weapon_type": "mount4"
            },
            {
                "force_id": "force_40",
                "force_position": "116.407534,39.822048",
                "force_type": "plane1",
                "fuel_cost": "0.424616",
                "max_distance": "12",
                "max_speed": "41",
                "min_speed": "35",
                "preparation_time": "12",
                "setup_cost": "0.387385",
                "weapon_num": "30",
                "weapon_type": "mount1"
            },
            {
                "force_id": "force_41",
                "force_position": "116.326626,39.807845",
                "force_type": "plane2",
                "fuel_cost": "0.062596",
                "max_distance": "34",
                "max_speed": "53",
                "min_speed": "34",
                "preparation_time": "28",
                "setup_cost": "0.198812",
                "weapon_num": "50,50",
                "weapon_type": "mount2,mount3"
            },
            {
                "force_id": "force_42",
                "force_position": "116.468169,39.815825",
                "force_type": "plane2",
                "fuel_cost": "0.378651",
                "max_distance": "33",
                "max_speed": "76",
                "min_speed": "28",
                "preparation_time": "23",
                "setup_cost": "0.932277",
                "weapon_num": "50,50",
                "weapon_type": "mount2,mount3"
            },
            {
                "force_id": "force_43",
                "force_position": "116.343424,39.936763",
                "force_type": "vehical1",
                "fuel_cost": "0.504679",
                "max_distance": "36",
                "max_speed": "50",
                "min_speed": "13",
                "preparation_time": "22",
                "setup_cost": "0.783501",
                "weapon_num": "40",
                "weapon_type": "mount4"
            },
            {
                "force_id": "force_44",
                "force_position": "116.384468,39.840570",
                "force_type": "plane2",
                "fuel_cost": "0.818576",
                "max_distance": "16",
                "max_speed": "62",
                "min_speed": "13",
                "preparation_time": "31",
                "setup_cost": "0.414105",
                "weapon_num": "50,50",
                "weapon_type": "mount2,mount3"
            },
            {
                "force_id": "force_45",
                "force_position": "116.477382,39.957250",
                "force_type": "plane2",
                "fuel_cost": "0.350899",
                "max_distance": "35",
                "max_speed": "74",
                "min_speed": "35",
                "preparation_time": "24",
                "setup_cost": "0.553589",
                "weapon_num": "50,50",
                "weapon_type": "mount2,mount3"
            },
            {
                "force_id": "force_46",
                "force_position": "116.321190,39.864684",
                "force_type": "plane1",
                "fuel_cost": "0.545272",
                "max_distance": "28",
                "max_speed": "43",
                "min_speed": "35",
                "preparation_time": "21",
                "setup_cost": "0.139489",
                "weapon_num": "30",
                "weapon_type": "mount1"
            },
            {
                "force_id": "force_47",
                "force_position": "116.477774,39.921123",
                "force_type": "vehical2",
                "fuel_cost": "0.995356",
                "max_distance": "29",
                "max_speed": "40",
                "min_speed": "34",
                "preparation_time": "23",
                "setup_cost": "0.043424",
                "weapon_num": "30",
                "weapon_type": "mount5"
            },
            {
                "force_id": "force_48",
                "force_position": "116.424624,39.967120",
                "force_type": "plane2",
                "fuel_cost": "0.070703",
                "max_distance": "11",
                "max_speed": "80",
                "min_speed": "17",
                "preparation_time": "21",
                "setup_cost": "0.549916",
                "weapon_num": "50,50",
                "weapon_type": "mount2,mount3"
            },
            {
                "force_id": "force_49",
                "force_position": "116.471321,40.030528",
                "force_type": "plane2",
                "fuel_cost": "0.655764",
                "max_distance": "27",
                "max_speed": "53",
                "min_speed": "21",
                "preparation_time": "38",
                "setup_cost": "0.942910",
                "weapon_num": "50,50",
                "weapon_type": "mount2,mount3"
            },
            {
                "force_id": "force_50",
                "force_position": "116.443269,40.029271",
                "force_type": "vehical1",
                "fuel_cost": "0.882980",
                "max_distance": "16",
                "max_speed": "77",
                "min_speed": "22",
                "preparation_time": "28",
                "setup_cost": "0.431237",
                "weapon_num": "40",
                "weapon_type": "mount4"
            },
            {
                "force_id": "force_51",
                "force_position": "116.463915,39.976494",
                "force_type": "vehical2",
                "fuel_cost": "0.611158",
                "max_distance": "10",
                "max_speed": "66",
                "min_speed": "19",
                "preparation_time": "31",
                "setup_cost": "0.488748",
                "weapon_num": "30",
                "weapon_type": "mount5"
            },
            {
                "force_id": "force_52",
                "force_position": "116.354479,39.793332",
                "force_type": "plane2",
                "fuel_cost": "0.533910",
                "max_distance": "26",
                "max_speed": "60",
                "min_speed": "11",
                "preparation_time": "21",
                "setup_cost": "0.452314",
                "weapon_num": "50,50",
                "weapon_type": "mount2,mount3"
            },
            {
                "force_id": "force_53",
                "force_position": "116.468112,39.959734",
                "force_type": "plane2",
                "fuel_cost": "0.721475",
                "max_distance": "24",
                "max_speed": "69",
                "min_speed": "34",
                "preparation_time": "26",
                "setup_cost": "0.881560",
                "weapon_num": "50,50",
                "weapon_type": "mount2,mount3"
            },
            {
                "force_id": "force_54",
                "force_position": "116.331717,39.940399",
                "force_type": "plane1",
                "fuel_cost": "0.174757",
                "max_distance": "13",
                "max_speed": "76",
                "min_speed": "29",
                "preparation_time": "25",
                "setup_cost": "0.179915",
                "weapon_num": "30",
                "weapon_type": "mount1"
            },
            {
                "force_id": "force_55",
                "force_position": "116.326999,39.807595",
                "force_type": "plane2",
                "fuel_cost": "0.017898",
                "max_distance": "19",
                "max_speed": "43",
                "min_speed": "39",
                "preparation_time": "39",
                "setup_cost": "0.262230",
                "weapon_num": "50,50",
                "weapon_type": "mount2,mount3"
            },
            {
                "force_id": "force_56",
                "force_position": "116.337876,39.800194",
                "force_type": "plane2",
                "fuel_cost": "0.610587",
                "max_distance": "37",
                "max_speed": "47",
                "min_speed": "21",
                "preparation_time": "23",
                "setup_cost": "0.629308",
                "weapon_num": "50,50",
                "weapon_type": "mount2,mount3"
            },
            {
                "force_id": "force_57",
                "force_position": "116.318652,39.780609",
                "force_type": "vehical1",
                "fuel_cost": "0.637013",
                "max_distance": "38",
                "max_speed": "63",
                "min_speed": "16",
                "preparation_time": "13",
                "setup_cost": "0.149825",
                "weapon_num": "40",
                "weapon_type": "mount4"
            },
            {
                "force_id": "force_58",
                "force_position": "116.328293,39.857496",
                "force_type": "vehical2",
                "fuel_cost": "0.081518",
                "max_distance": "26",
                "max_speed": "74",
                "min_speed": "17",
                "preparation_time": "13",
                "setup_cost": "0.381616",
                "weapon_num": "30",
                "weapon_type": "mount5"
            },
            {
                "force_id": "force_59",
                "force_position": "116.471185,40.016079",
                "force_type": "plane2",
                "fuel_cost": "0.569110",
                "max_distance": "25",
                "max_speed": "54",
                "min_speed": "13",
                "preparation_time": "14",
                "setup_cost": "0.243664",
                "weapon_num": "50,50",
                "weapon_type": "mount2,mount3"
            },
            {
                "force_id": "force_60",
                "force_position": "116.432131,39.972055",
                "force_type": "vehical1",
                "fuel_cost": "0.604110",
                "max_distance": "30",
                "max_speed": "78",
                "min_speed": "22",
                "preparation_time": "40",
                "setup_cost": "0.741140",
                "weapon_num": "40",
                "weapon_type": "mount4"
            },
            {
                "force_id": "force_61",
                "force_position": "116.414280,39.787772",
                "force_type": "plane2",
                "fuel_cost": "0.915768",
                "max_distance": "22",
                "max_speed": "80",
                "min_speed": "34",
                "preparation_time": "19",
                "setup_cost": "0.912831",
                "weapon_num": "50,50",
                "weapon_type": "mount2,mount3"
            },
            {
                "force_id": "force_62",
                "force_position": "116.366577,39.821047",
                "force_type": "vehical1",
                "fuel_cost": "0.985232",
                "max_distance": "19",
                "max_speed": "69",
                "min_speed": "31",
                "preparation_time": "32",
                "setup_cost": "0.760330",
                "weapon_num": "40",
                "weapon_type": "mount4"
            },
            {
                "force_id": "force_63",
                "force_position": "116.385260,40.010904",
                "force_type": "vehical2",
                "fuel_cost": "0.117308",
                "max_distance": "22",
                "max_speed": "47",
                "min_speed": "10",
                "preparation_time": "17",
                "setup_cost": "0.813863",
                "weapon_num": "30",
                "weapon_type": "mount5"
            },
            {
                "force_id": "force_64",
                "force_position": "116.355655,39.874039",
                "force_type": "vehical2",
                "fuel_cost": "0.922275",
                "max_distance": "39",
                "max_speed": "72",
                "min_speed": "39",
                "preparation_time": "13",
                "setup_cost": "0.646370",
                "weapon_num": "30",
                "weapon_type": "mount5"
            },
            {
                "force_id": "force_65",
                "force_position": "116.463321,40.006328",
                "force_type": "vehical2",
                "fuel_cost": "0.369413",
                "max_distance": "28",
                "max_speed": "52",
                "min_speed": "18",
                "preparation_time": "12",
                "setup_cost": "0.568155",
                "weapon_num": "30",
                "weapon_type": "mount5"
            },
            {
                "force_id": "force_66",
                "force_position": "116.408970,39.988891",
                "force_type": "vehical1",
                "fuel_cost": "0.952193",
                "max_distance": "38",
                "max_speed": "66",
                "min_speed": "29",
                "preparation_time": "11",
                "setup_cost": "0.176079",
                "weapon_num": "40",
                "weapon_type": "mount4"
            },
            {
                "force_id": "force_67",
                "force_position": "116.455125,39.978104",
                "force_type": "vehical2",
                "fuel_cost": "0.491326",
                "max_distance": "35",
                "max_speed": "45",
                "min_speed": "23",
                "preparation_time": "13",
                "setup_cost": "0.500773",
                "weapon_num": "30",
                "weapon_type": "mount5"
            },
            {
                "force_id": "force_68",
                "force_position": "116.456532,39.910919",
                "force_type": "plane1",
                "fuel_cost": "0.463974",
                "max_distance": "11",
                "max_speed": "49",
                "min_speed": "31",
                "preparation_time": "21",
                "setup_cost": "0.894586",
                "weapon_num": "30",
                "weapon_type": "mount1"
            },
            {
                "force_id": "force_69",
                "force_position": "116.378774,39.886416",
                "force_type": "plane2",
                "fuel_cost": "0.548683",
                "max_distance": "14",
                "max_speed": "47",
                "min_speed": "29",
                "preparation_time": "38",
                "setup_cost": "0.585140",
                "weapon_num": "50,50",
                "weapon_type": "mount2,mount3"
            },
            {
                "force_id": "force_70",
                "force_position": "116.452872,39.810211",
                "force_type": "vehical1",
                "fuel_cost": "0.969307",
                "max_distance": "31",
                "max_speed": "41",
                "min_speed": "21",
                "preparation_time": "18",
                "setup_cost": "0.717786",
                "weapon_num": "40",
                "weapon_type": "mount4"
            },
            {
                "force_id": "force_71",
                "force_position": "116.329769,40.029898",
                "force_type": "vehical2",
                "fuel_cost": "0.240770",
                "max_distance": "21",
                "max_speed": "78",
                "min_speed": "20",
                "preparation_time": "38",
                "setup_cost": "0.818254",
                "weapon_num": "30",
                "weapon_type": "mount5"
            },
            {
                "force_id": "force_72",
                "force_position": "116.450074,39.824110",
                "force_type": "plane2",
                "fuel_cost": "0.652246",
                "max_distance": "38",
                "max_speed": "48",
                "min_speed": "15",
                "preparation_time": "24",
                "setup_cost": "0.048255",
                "weapon_num": "50,50",
                "weapon_type": "mount2,mount3"
            },
            {
                "force_id": "force_73",
                "force_position": "116.311429,39.980244",
                "force_type": "vehical1",
                "fuel_cost": "0.948513",
                "max_distance": "13",
                "max_speed": "64",
                "min_speed": "22",
                "preparation_time": "10",
                "setup_cost": "0.910560",
                "weapon_num": "40",
                "weapon_type": "mount4"
            },
            {
                "force_id": "force_74",
                "force_position": "116.483859,39.799975",
                "force_type": "vehical2",
                "fuel_cost": "0.433651",
                "max_distance": "40",
                "max_speed": "49",
                "min_speed": "25",
                "preparation_time": "15",
                "setup_cost": "0.759613",
                "weapon_num": "30",
                "weapon_type": "mount5"
            },
            {
                "force_id": "force_75",
                "force_position": "116.432631,39.879239",
                "force_type": "vehical1",
                "fuel_cost": "0.507077",
                "max_distance": "32",
                "max_speed": "51",
                "min_speed": "35",
                "preparation_time": "27",
                "setup_cost": "0.480667",
                "weapon_num": "40",
                "weapon_type": "mount4"
            },
            {
                "force_id": "force_76",
                "force_position": "116.392672,39.782690",
                "force_type": "vehical2",
                "fuel_cost": "0.877047",
                "max_distance": "32",
                "max_speed": "65",
                "min_speed": "25",
                "preparation_time": "32",
                "setup_cost": "0.782099",
                "weapon_num": "30",
                "weapon_type": "mount5"
            },
            {
                "force_id": "force_77",
                "force_position": "116.462154,39.785751",
                "force_type": "vehical2",
                "fuel_cost": "0.229527",
                "max_distance": "26",
                "max_speed": "63",
                "min_speed": "32",
                "preparation_time": "23",
                "setup_cost": "0.444478",
                "weapon_num": "30",
                "weapon_type": "mount5"
            },
            {
                "force_id": "force_78",
                "force_position": "116.432852,39.801403",
                "force_type": "vehical1",
                "fuel_cost": "0.876791",
                "max_distance": "15",
                "max_speed": "72",
                "min_speed": "18",
                "preparation_time": "24",
                "setup_cost": "0.739961",
                "weapon_num": "40",
                "weapon_type": "mount4"
            },
            {
                "force_id": "force_79",
                "force_position": "116.326735,39.880617",
                "force_type": "plane1",
                "fuel_cost": "0.537425",
                "max_distance": "35",
                "max_speed": "79",
                "min_speed": "19",
                "preparation_time": "31",
                "setup_cost": "0.605079",
                "weapon_num": "30",
                "weapon_type": "mount1"
            },
            {
                "force_id": "force_80",
                "force_position": "116.422601,39.929937",
                "force_type": "vehical2",
                "fuel_cost": "0.005733",
                "max_distance": "22",
                "max_speed": "69",
                "min_speed": "14",
                "preparation_time": "36",
                "setup_cost": "0.124626",
                "weapon_num": "30",
                "weapon_type": "mount5"
            },
            {
                "force_id": "force_81",
                "force_position": "116.465609,39.926523",
                "force_type": "vehical1",
                "fuel_cost": "0.321613",
                "max_distance": "16",
                "max_speed": "69",
                "min_speed": "18",
                "preparation_time": "36",
                "setup_cost": "0.809224",
                "weapon_num": "40",
                "weapon_type": "mount4"
            },
            {
                "force_id": "force_82",
                "force_position": "116.392320,39.879358",
                "force_type": "plane1",
                "fuel_cost": "0.320734",
                "max_distance": "14",
                "max_speed": "47",
                "min_speed": "25",
                "preparation_time": "37",
                "setup_cost": "0.813853",
                "weapon_num": "30",
                "weapon_type": "mount1"
            },
            {
                "force_id": "force_83",
                "force_position": "116.376512,39.796126",
                "force_type": "vehical1",
                "fuel_cost": "0.647129",
                "max_distance": "33",
                "max_speed": "66",
                "min_speed": "26",
                "preparation_time": "39",
                "setup_cost": "0.279588",
                "weapon_num": "40",
                "weapon_type": "mount4"
            },
            {
                "force_id": "force_84",
                "force_position": "116.394104,40.038371",
                "force_type": "plane1",
                "fuel_cost": "0.354953",
                "max_distance": "22",
                "max_speed": "62",
                "min_speed": "20",
                "preparation_time": "15",
                "setup_cost": "0.252009",
                "weapon_num": "30",
                "weapon_type": "mount1"
            },
            {
                "force_id": "force_85",
                "force_position": "116.399887,39.826863",
                "force_type": "plane1",
                "fuel_cost": "0.489872",
                "max_distance": "32",
                "max_speed": "55",
                "min_speed": "10",
                "preparation_time": "20",
                "setup_cost": "0.556447",
                "weapon_num": "30",
                "weapon_type": "mount1"
            },
            {
                "force_id": "force_86",
                "force_position": "116.433163,39.928487",
                "force_type": "plane2",
                "fuel_cost": "0.813431",
                "max_distance": "38",
                "max_speed": "76",
                "min_speed": "13",
                "preparation_time": "20",
                "setup_cost": "0.241948",
                "weapon_num": "50,50",
                "weapon_type": "mount2,mount3"
            },
            {
                "force_id": "force_87",
                "force_position": "116.344943,39.942900",
                "force_type": "plane2",
                "fuel_cost": "0.764999",
                "max_distance": "32",
                "max_speed": "70",
                "min_speed": "23",
                "preparation_time": "30",
                "setup_cost": "0.704997",
                "weapon_num": "50,50",
                "weapon_type": "mount2,mount3"
            },
            {
                "force_id": "force_88",
                "force_position": "116.371562,39.791136",
                "force_type": "plane2",
                "fuel_cost": "0.263425",
                "max_distance": "27",
                "max_speed": "80",
                "min_speed": "34",
                "preparation_time": "32",
                "setup_cost": "0.537127",
                "weapon_num": "50,50",
                "weapon_type": "mount2,mount3"
            },
            {
                "force_id": "force_89",
                "force_position": "116.334308,39.997003",
                "force_type": "vehical2",
                "fuel_cost": "0.631765",
                "max_distance": "21",
                "max_speed": "56",
                "min_speed": "36",
                "preparation_time": "12",
                "setup_cost": "0.691469",
                "weapon_num": "30",
                "weapon_type": "mount5"
            },
            {
                "force_id": "force_90",
                "force_position": "116.396480,39.997562",
                "force_type": "plane1",
                "fuel_cost": "0.608570",
                "max_distance": "11",
                "max_speed": "78",
                "min_speed": "16",
                "preparation_time": "31",
                "setup_cost": "0.329548",
                "weapon_num": "30",
                "weapon_type": "mount1"
            },
            {
                "force_id": "force_91",
                "force_position": "116.328497,39.972853",
                "force_type": "vehical2",
                "fuel_cost": "0.537571",
                "max_distance": "22",
                "max_speed": "56",
                "min_speed": "17",
                "preparation_time": "34",
                "setup_cost": "0.861543",
                "weapon_num": "30",
                "weapon_type": "mount5"
            },
            {
                "force_id": "force_92",
                "force_position": "116.336302,39.942975",
                "force_type": "plane1",
                "fuel_cost": "0.407587",
                "max_distance": "10",
                "max_speed": "40",
                "min_speed": "26",
                "preparation_time": "26",
                "setup_cost": "0.601251",
                "weapon_num": "30",
                "weapon_type": "mount1"
            },
            {
                "force_id": "force_93",
                "force_position": "116.419360,39.898926",
                "force_type": "vehical2",
                "fuel_cost": "0.871290",
                "max_distance": "37",
                "max_speed": "74",
                "min_speed": "35",
                "preparation_time": "15",
                "setup_cost": "0.142287",
                "weapon_num": "30",
                "weapon_type": "mount5"
            },
            {
                "force_id": "force_94",
                "force_position": "116.431267,39.943455",
                "force_type": "vehical1",
                "fuel_cost": "0.323985",
                "max_distance": "10",
                "max_speed": "60",
                "min_speed": "21",
                "preparation_time": "21",
                "setup_cost": "0.124971",
                "weapon_num": "40",
                "weapon_type": "mount4"
            },
            {
                "force_id": "force_95",
                "force_position": "116.327207,39.955179",
                "force_type": "plane1",
                "fuel_cost": "0.577196",
                "max_distance": "36",
                "max_speed": "47",
                "min_speed": "10",
                "preparation_time": "19",
                "setup_cost": "0.558762",
                "weapon_num": "30",
                "weapon_type": "mount1"
            },
            {
                "force_id": "force_96",
                "force_position": "116.319044,39.837886",
                "force_type": "vehical2",
                "fuel_cost": "0.548445",
                "max_distance": "39",
                "max_speed": "73",
                "min_speed": "19",
                "preparation_time": "30",
                "setup_cost": "0.899121",
                "weapon_num": "30",
                "weapon_type": "mount5"
            },
            {
                "force_id": "force_97",
                "force_position": "116.394768,39.958315",
                "force_type": "plane2",
                "fuel_cost": "0.764127",
                "max_distance": "25",
                "max_speed": "44",
                "min_speed": "38",
                "preparation_time": "10",
                "setup_cost": "0.828141",
                "weapon_num": "50,50",
                "weapon_type": "mount2,mount3"
            },
            {
                "force_id": "force_98",
                "force_position": "116.477907,39.882487",
                "force_type": "plane1",
                "fuel_cost": "0.772137",
                "max_distance": "39",
                "max_speed": "42",
                "min_speed": "33",
                "preparation_time": "37",
                "setup_cost": "0.777609",
                "weapon_num": "30",
                "weapon_type": "mount1"
            },
            {
                "force_id": "force_99",
                "force_position": "116.436814,39.904036",
                "force_type": "plane1",
                "fuel_cost": "0.096593",
                "max_distance": "16",
                "max_speed": "58",
                "min_speed": "29",
                "preparation_time": "18",
                "setup_cost": "0.667528",
                "weapon_num": "30",
                "weapon_type": "mount1"
            },
            {
                "force_id": "force_100",
                "force_position": "116.385423,39.804827",
                "force_type": "vehical1",
                "fuel_cost": "0.009856",
                "max_distance": "38",
                "max_speed": "56",
                "min_speed": "15",
                "preparation_time": "27",
                "setup_cost": "0.651009",
                "weapon_num": "40",
                "weapon_type": "mount4"
            },
            {
                "force_id": "force_101",
                "force_position": "116.420126,39.925265",
                "force_type": "vehical1",
                "fuel_cost": "0.716012",
                "max_distance": "35",
                "max_speed": "46",
                "min_speed": "19",
                "preparation_time": "37",
                "setup_cost": "0.456189",
                "weapon_num": "40",
                "weapon_type": "mount4"
            },
            {
                "force_id": "force_102",
                "force_position": "116.418379,39.898336",
                "force_type": "vehical1",
                "fuel_cost": "0.994913",
                "max_distance": "25",
                "max_speed": "75",
                "min_speed": "40",
                "preparation_time": "22",
                "setup_cost": "0.905756",
                "weapon_num": "40",
                "weapon_type": "mount4"
            },
            {
                "force_id": "force_103",
                "force_position": "116.414732,40.021392",
                "force_type": "plane2",
                "fuel_cost": "0.391811",
                "max_distance": "18",
                "max_speed": "56",
                "min_speed": "23",
                "preparation_time": "11",
                "setup_cost": "0.148104",
                "weapon_num": "50,50",
                "weapon_type": "mount2,mount3"
            },
            {
                "force_id": "force_104",
                "force_position": "116.486733,39.856247",
                "force_type": "plane1",
                "fuel_cost": "0.083780",
                "max_distance": "24",
                "max_speed": "43",
                "min_speed": "11",
                "preparation_time": "20",
                "setup_cost": "0.824868",
                "weapon_num": "30",
                "weapon_type": "mount1"
            }
        ],
        "mount_attribute": [
            {
                "is_occupypied": "0",
                "load_list": "load5",
                "mount_cost": "1600",
                "mount_name": "mount1",
                "mount_type_name": "mount5",
                "range": "640",
                "required_time": "300",
                "stock_num": "10000",
                "test": "1"
            },
            {
                "is_occupypied": "0",
                "load_list": "load5",
                "mount_cost": "1600",
                "mount_name": "mount2",
                "mount_type_name": "mount5",
                "range": "640",
                "required_time": "300",
                "stock_num": "10000",
                "test": "1"
            },
            {
                "is_occupypied": "0",
                "load_list": "load3",
                "mount_cost": "1600",
                "mount_name": "mount3",
                "mount_type_name": "mount3",
                "range": "640",
                "required_time": "300",
                "stock_num": "10000",
                "test": "1"
            },
            {
                "is_occupypied": "0",
                "load_list": "load2",
                "mount_cost": "1600",
                "mount_name": "mount4",
                "mount_type_name": "mount2",
                "range": "640",
                "required_time": "300",
                "stock_num": "10000",
                "test": "1"
            },
            {
                "is_occupypied": "0",
                "load_list": "load2",
                "mount_cost": "1600",
                "mount_name": "mount5",
                "mount_type_name": "mount2",
                "range": "640",
                "required_time": "300",
                "stock_num": "10000",
                "test": "1"
            },
            {
                "is_occupypied": "0",
                "load_list": "load1",
                "mount_cost": "1600",
                "mount_name": "mount6",
                "mount_type_name": "mount1",
                "range": "640",
                "required_time": "300",
                "stock_num": "10000",
                "test": "1"
            },
            {
                "is_occupypied": "0",
                "load_list": "load5",
                "mount_cost": "1600",
                "mount_name": "mount7",
                "mount_type_name": "mount5",
                "range": "640",
                "required_time": "300",
                "stock_num": "10000",
                "test": "1"
            },
            {
                "is_occupypied": "0",
                "load_list": "load5",
                "mount_cost": "1600",
                "mount_name": "mount8",
                "mount_type_name": "mount5",
                "range": "640",
                "required_time": "300",
                "stock_num": "10000",
                "test": "1"
            },
            {
                "is_occupypied": "0",
                "load_list": "load1",
                "mount_cost": "1600",
                "mount_name": "mount9",
                "mount_type_name": "mount1",
                "range": "640",
                "required_time": "300",
                "stock_num": "10000",
                "test": "1"
            },
            {
                "is_occupypied": "0",
                "load_list": "load5",
                "mount_cost": "1600",
                "mount_name": "mount10",
                "mount_type_name": "mount5",
                "range": "640",
                "required_time": "300",
                "stock_num": "10000",
                "test": "1"
            }
        ],
        "mount_type": [
            {
                "grp_num_ub": "2",
                "interval_time": "40",
                "mount_type_name": "mount1"
            },
            {
                "grp_num_ub": "2",
                "interval_time": "40",
                "mount_type_name": "mount2"
            },
            {
                "grp_num_ub": "2",
                "interval_time": "40",
                "mount_type_name": "mount3"
            },
            {
                "grp_num_ub": "2",
                "interval_time": "40",
                "mount_type_name": "mount4"
            },
            {
                "grp_num_ub": "2",
                "interval_time": "40",
                "mount_type_name": "mount5"
            }
        ],
        "muilti_plan_parameter": {
            "costfailure": "0",
            "costfair": "0",
            "costoil": "0",
            "costuse": "0",
            "plan_name": "1",
            "plan_type": "economic_first",
            "rate": "1",
            "status": "true"
        },
        "target_list": [
            {
                "appearance_time": "2025-01-01 00:00:00",
                "batch_id": "batch0",
                "leadtime": "23",
                "target_id": "target7",
                "target_position": "116.343248,39.788764",
                "target_priority": "0.737968",
                "target_type": "target_type1",
                "target_type_max_mount": "3",
                "weapon_num": "200",
                "weapon_type": "mount3#load3"
            },
            {
                "appearance_time": "2025-01-01 00:00:00",
                "batch_id": "batch0",
                "leadtime": "35",
                "target_id": "target6",
                "target_position": "116.310306,39.985853",
                "target_priority": "0.578517",
                "target_type": "target_type2",
                "target_type_max_mount": "3",
                "weapon_num": "120",
                "weapon_type": "mount1#load1"
            },
            {
                "appearance_time": "2025-01-01 00:00:00",
                "batch_id": "batch0",
                "leadtime": "20",
                "target_id": "target5",
                "target_position": "116.445265,40.016053",
                "target_priority": "0.290123",
                "target_type": "target_type3",
                "target_type_max_mount": "3",
                "weapon_num": "200",
                "weapon_type": "mount3#load3"
            },
            {
                "appearance_time": "2025-01-01 00:00:00",
                "batch_id": "batch0",
                "leadtime": "19",
                "target_id": "target0",
                "target_position": "116.372517,40.035855",
                "target_priority": "0.658775",
                "target_type": "target_type3",
                "target_type_max_mount": "3",
                "weapon_num": "150",
                "weapon_type": "mount5#load5"
            },
            {
                "appearance_time": "2025-01-01 00:00:00",
                "batch_id": "batch0",
                "leadtime": "25",
                "target_id": "target2",
                "target_position": "116.342735,39.908762",
                "target_priority": "0.207424",
                "target_type": "target_type1",
                "target_type_max_mount": "3",
                "weapon_num": "150",
                "weapon_type": "mount5#load5"
            },
            {
                "appearance_time": "2025-01-01 00:00:00",
                "batch_id": "batch0",
                "leadtime": "36",
                "target_id": "target3",
                "target_position": "116.342116,40.013869",
                "target_priority": "0.208876",
                "target_type": "target_type2",
                "target_type_max_mount": "3",
                "weapon_num": "240",
                "weapon_type": "mount4#load4"
            },
            {
                "appearance_time": "2025-01-01 00:00:00",
                "batch_id": "batch0",
                "leadtime": "22",
                "target_id": "target8",
                "target_position": "116.417254,39.895146",
                "target_priority": "0.349819",
                "target_type": "target_type3",
                "target_type_max_mount": "3",
                "weapon_num": "200",
                "weapon_type": "mount3#load3"
            },
            {
                "appearance_time": "2025-01-01 00:00:00",
                "batch_id": "batch0",
                "leadtime": "34",
                "target_id": "target4",
                "target_position": "116.332932,39.878921",
                "target_priority": "0.945021",
                "target_type": "target_type3",
                "target_type_max_mount": "3",
                "weapon_num": "120",
                "weapon_type": "mount1#load1"
            }
        ],
        "trainning_frequency": null,
        "warhead_cost": {
            "load_type": "0.0"
        }
    },
    "historical_plan": {
        "plan_id": "plan_43_primary",
        "resource_utilization": 0.380952,
        "target_coverage": 1.0,
        "total_cost": 18.10132,
        "total_time": 0.467476
    },
    "scenario_features": {
        "decision_preference": "difference",
        "num_resource_types": 9,
        "num_resources": 105,
        "num_target_types": 3,
        "num_targets": 8,
        "original_scenario_id": 43,
        "planning_type": "secondary",
        "scenario_id": 1039,
        "target_change_ratio": -0.10000000149011612,
        "urgency_level": 0.5112451910972595
    }
}